LICENSE.md
README.md
setup.py
hebpipe/__init__.py
hebpipe/check_len.py
hebpipe/clean_meta.py
hebpipe/conll18_ud_eval.py
hebpipe/eval_morph.py
hebpipe/heb_pipe.py
hebpipe.egg-info/PKG-INFO
hebpipe.egg-info/SOURCES.txt
hebpipe.egg-info/dependency_links.txt
hebpipe.egg-info/requires.txt
hebpipe.egg-info/top_level.txt
hebpipe/bin/binary_dependencies_go_here.txt
hebpipe/data/SPMRL_dev_gold.tab
hebpipe/data/SPMRL_dev_plain.tab
hebpipe/data/SPMRL_test_gold.tab
hebpipe/data/SPMRL_test_plain.tab
hebpipe/data/SPMRL_train_gold.tab
hebpipe/data/SPMRL_train_plain.tab
hebpipe/data/Wiki5K_test_gold.tab
hebpipe/data/Wiki5K_test_plain.tab
hebpipe/data/char_vocab.txt
hebpipe/data/heb.binyan
hebpipe/data/heb.conf
hebpipe/data/heb.frq
hebpipe/data/heb.lemma
hebpipe/data/heb.lex
hebpipe/data/heb_abbr.tab
hebpipe/data/heb_lemma_lex.tab
hebpipe/data/heb_train_seg_all.tab
hebpipe/data/heb_train_tb.conll10
hebpipe/data/make_lemma_lex.py
hebpipe/data/mtldatafile_dev.tab
hebpipe/data/mtldatafile_train.tab
hebpipe/data/postprocess_parsed.ini
hebpipe/data/sentsplit_postag_dev_gold.tab
hebpipe/data/sentsplit_postag_train_gold.tab
hebpipe/eval/__init__.py
hebpipe/eval/eval_parsing.py
hebpipe/eval/eval_tokenization.py
hebpipe/eval/f_score_segs.py
hebpipe/lib/__init__.py
hebpipe/lib/_version.py
hebpipe/lib/append_column.py
hebpipe/lib/binarize_tags.py
hebpipe/lib/depedit.py
hebpipe/lib/dropout.py
hebpipe/lib/harvest_tt_sgml.py
hebpipe/lib/morph_trankit.py
hebpipe/lib/mtlmodel - new.py
hebpipe/lib/mtlmodel.py
hebpipe/lib/mtlmodel_lemma.py
hebpipe/lib/partial_morph.ini
hebpipe/lib/preprocess.py
hebpipe/lib/reorder_sgml.py
hebpipe/lib/sent_split.py
hebpipe/lib/timing.py
hebpipe/lib/tt2conll.py
hebpipe/lib/whitespace_tokenize.py
hebpipe/lib/crfutils/__init__.py
hebpipe/lib/crfutils/crf.py
hebpipe/lib/crfutils/viterbi.py
hebpipe/lib/xrenner/__init__.py
hebpipe/lib/xrenner/xrenner.py
hebpipe/lib/xrenner/modules/__init__.py
hebpipe/lib/xrenner/modules/depedit.py
hebpipe/lib/xrenner/modules/get_models.py
hebpipe/lib/xrenner/modules/timing.py
hebpipe/lib/xrenner/modules/xrenner_classes.py
hebpipe/lib/xrenner/modules/xrenner_classify.py
