Metadata-Version: 2.1
Name: hebpipe
Version: 4.0.2.0
Summary: A pipeline for Hebrew NLP
Home-page: https://github.com/amir-zeldes/HebPipe
Download-URL: https://github.com/amir-zeldes/HebPipe/releases/tag/v4.0.2.0
Author: Amir Zeldes
Author-email: amir.zeldes@georgetown.edu
License: Apache License, Version 2.0
Keywords: NLP,Hebrew,segmentation,tokenization,tagging,parsing,morphology,POS,lemmatization
Classifier: Programming Language :: Python
Classifier: Programming Language :: Python :: 2
Classifier: Programming Language :: Python :: 3
Classifier: License :: OSI Approved :: Apache Software License
Classifier: Operating System :: OS Independent
License-File: LICENSE.md
